{
  "stories": [
    {
      "name": "Art & Economy",
      "created_at": "2022-01-21T07:32:18.937Z",
      "published_at": "2022-01-21T10:48:32.000Z",
      "id": 100297966,
      "uuid": "8f1e3d4e-1ae4-4e69-a019-21c55abed522",
      "content": {
        "_uid": "c7655568-b071-4b81-914a-5e8258f378f2",
        "link": "https://www.kunst-kultur-management.at",
        "component": "page_department",
        "part_of_institute": {
          "name": "Institut für Sprachkunst",
          "id": "4507a8e6-ff4c-4c43-a324-9986818a9a4d",
          "url": "",
          "linktype": "story",
          "fieldtype": "multilink",
          "cached_url": "2022/data/data-institutes/institut-fuer-sprachkunst"
        }
      },
      "slug": "art-economy",
      "full_slug": "abteilungen/art-economy",
      "sort_by_date": null,
      "position": -350,
      "tag_list": [],
      "is_startpage": false,
      "parent_id": 95693957,
      "meta_data": null,
      "group_id": "0f002a06-1d69-41fb-bd23-1b3a0b5765e9",
      "first_published_at": "2022-01-21T07:33:54.437Z",
      "release_id": null,
      "lang": "default",
      "path": null,
      "alternates": [],
      "default_full_slug": null,
      "translated_slugs": null
    },
    {
      "name": "Vienna Master of Arts in Applied Human Rights",
      "created_at": "2022-01-21T07:31:53.425Z",
      "published_at": "2022-01-21T10:48:32.000Z",
      "id": 100297963,
      "uuid": "c69e7656-6c75-42b6-854a-d2e132f5e187",
      "content": {
        "_uid": "674bda11-da1f-41bf-a5fb-c022cc4c22d7",
        "link": "https://appliedhumanrights.uni-ak.ac.at",
        "component": "page_department",
        "part_of_institute": {
          "name": "Institut für Sprachkunst",
          "id": "4507a8e6-ff4c-4c43-a324-9986818a9a4d",
          "url": "",
          "linktype": "story",
          "fieldtype": "multilink",
          "cached_url": "2022/data/data-institutes/institut-fuer-sprachkunst"
        }
      },
      "slug": "vienna-master-of-arts-in-applied-human-rights",
      "full_slug": "abteilungen/vienna-master-of-arts-in-applied-human-rights",
      "sort_by_date": null,
      "position": -340,
      "tag_list": [],
      "is_startpage": false,
      "parent_id": 95693957,
      "meta_data": null,
      "group_id": "1dae9746-af05-48b3-922e-f62e8e26a539",
      "first_published_at": "2022-01-21T07:33:54.437Z",
      "release_id": null,
      "lang": "default",
      "path": null,
      "alternates": [],
      "default_full_slug": null,
      "translated_slugs": null
    },
    {
      "name": "ecm",
      "created_at": "2022-01-21T07:31:40.895Z",
      "published_at": "2022-01-21T10:48:32.000Z",
      "id": 100297962,
      "uuid": "be815895-c8bd-46c0-9c5c-750288537155",
      "content": {
        "_uid": "520a5132-5c49-4019-9193-6cea0cb5181d",
        "link": "https://ecm.ac.at",
        "component": "page_department",
        "part_of_institute": {
          "name": "Institut für Sprachkunst",
          "id": "4507a8e6-ff4c-4c43-a324-9986818a9a4d",
          "url": "",
          "linktype": "story",
          "fieldtype": "multilink",
          "cached_url": "2022/data/data-institutes/institut-fuer-sprachkunst"
        }
      },
      "slug": "ecm",
      "full_slug": "abteilungen/ecm",
      "sort_by_date": null,
      "position": -330,
      "tag_list": [],
      "is_startpage": false,
      "parent_id": 95693957,
      "meta_data": null,
      "group_id": "d5f0e19a-7b85-427b-a30b-4bd274855083",
      "first_published_at": "2022-01-21T07:33:54.437Z",
      "release_id": null,
      "lang": "default",
      "path": null,
      "alternates": [],
      "default_full_slug": null,
      "translated_slugs": null
    },
    {
      "name": "Zentrum Fokus Forschung",
      "created_at": "2022-01-21T07:31:31.352Z",
      "published_at": "2022-01-21T10:48:32.000Z",
      "id": 100297961,
      "uuid": "5978a50f-841b-41bf-a6fa-db6ac065ef96",
      "content": {
        "_uid": "d86916b8-51fe-46b8-9036-6dfe7417b981",
        "link": "https://zentrumfokusforschung.uni-ak.ac.at/en/",
        "component": "page_department",
        "part_of_institute": {
          "name": "Institut für Sprachkunst",
          "id": "4507a8e6-ff4c-4c43-a324-9986818a9a4d",
          "url": "",
          "linktype": "story",
          "fieldtype": "multilink",
          "cached_url": "2022/data/data-institutes/institut-fuer-sprachkunst"
        }
      },
      "slug": "zentrum-fokus-forschung",
      "full_slug": "abteilungen/zentrum-fokus-forschung",
      "sort_by_date": null,
      "position": -320,
      "tag_list": [],
      "is_startpage": false,
      "parent_id": 95693957,
      "meta_data": null,
      "group_id": "764aa00b-1b5b-4aec-8a2a-83595c576c60",
      "first_published_at": "2022-01-21T07:33:54.437Z",
      "release_id": null,
      "lang": "default",
      "path": null,
      "alternates": [],
      "default_full_slug": null,
      "translated_slugs": null
    },
    {
      "name": "Sprachkunst",
      "created_at": "2022-01-21T07:31:18.332Z",
      "published_at": "2022-01-21T10:48:32.000Z",
      "id": 100297960,
      "uuid": "401f6031-a20f-4005-9aee-552d2bf8190f",
      "content": {
        "_uid": "82233621-f257-489a-9dd1-e2bfd8a7df8d",
        "link": "https://sprachkunst.uni-ak.ac.at",
        "component": "page_department",
        "part_of_institute": {
          "name": "Institut für Sprachkunst",
          "id": "4507a8e6-ff4c-4c43-a324-9986818a9a4d",
          "url": "",
          "linktype": "story",
          "fieldtype": "multilink",
          "cached_url": "2022/data/data-institutes/institut-fuer-sprachkunst"
        }
      },
      "slug": "sprachkunst",
      "full_slug": "abteilungen/sprachkunst",
      "sort_by_date": null,
      "position": -310,
      "tag_list": [],
      "is_startpage": false,
      "parent_id": 95693957,
      "meta_data": null,
      "group_id": "3f770ca2-9005-4e75-b381-b95b85585801",
      "first_published_at": "2022-01-21T07:33:54.437Z",
      "release_id": null,
      "lang": "default",
      "path": null,
      "alternates": [],
      "default_full_slug": null,
      "translated_slugs": null
    },
    {
      "name": "International Programmes in Sustainable Developments",
      "created_at": "2022-01-21T07:31:08.101Z",
      "published_at": "2022-01-21T10:48:32.000Z",
      "id": 100297905,
      "uuid": "9f75e24d-8be7-4e11-88be-fed0abdc09c2",
      "content": {
        "_uid": "b1c31a48-9a07-47d5-ad2f-641e5a7449b2",
        "link": "https://ipsd.uni-ak.ac.at",
        "component": "page_department",
        "part_of_institute": {
          "name": "Institut für Kunst & Gesellschaft",
          "id": "1700b229-93dd-40d1-af1e-3553e880743b",
          "url": "",
          "linktype": "story",
          "fieldtype": "multilink",
          "cached_url": "2022/data/data-institutes/institut-fuer-kunst-gesellschaft"
        }
      },
      "slug": "international-programmes-in-sustainable-developments",
      "full_slug": "abteilungen/international-programmes-in-sustainable-developments",
      "sort_by_date": null,
      "position": -300,
      "tag_list": [],
      "is_startpage": false,
      "parent_id": 95693957,
      "meta_data": null,
      "group_id": "dab3d320-ab76-4336-a350-a1fe58462382",
      "first_published_at": "2022-01-21T07:33:54.437Z",
      "release_id": null,
      "lang": "default",
      "path": null,
      "alternates": [],
      "default_full_slug": null,
      "translated_slugs": null
    },
    {
      "name": "Social Design – Arts as Urban Innovation",
      "created_at": "2022-01-21T07:30:57.146Z",
      "published_at": "2022-01-21T10:48:32.000Z",
      "id": 100297896,
      "uuid": "b1391ded-6324-43a7-9f75-b61c298243a0",
      "content": {
        "_uid": "48e3828c-35ab-485f-9f2f-d2f3b5e43464",
        "link": "http://socialdesign.ac.at",
        "component": "page_department",
        "part_of_institute": {
          "name": "Institut für Kunst & Gesellschaft",
          "id": "1700b229-93dd-40d1-af1e-3553e880743b",
          "url": "",
          "linktype": "story",
          "fieldtype": "multilink",
          "cached_url": "2022/data/data-institutes/institut-fuer-kunst-gesellschaft"
        }
      },
      "slug": "social-design-arts-as-urban-innovation",
      "full_slug": "abteilungen/social-design-arts-as-urban-innovation",
      "sort_by_date": null,
      "position": -290,
      "tag_list": [],
      "is_startpage": false,
      "parent_id": 95693957,
      "meta_data": null,
      "group_id": "4a55b365-95fb-4567-bac9-404f0066343c",
      "first_published_at": "2022-01-21T07:33:54.437Z",
      "release_id": null,
      "lang": "default",
      "path": null,
      "alternates": [],
      "default_full_slug": null,
      "translated_slugs": null
    },
    {
      "name": "Cross-Disciplinary Strategies",
      "created_at": "2022-01-21T07:30:45.415Z",
      "published_at": "2022-01-21T10:48:32.000Z",
      "id": 100297895,
      "uuid": "9422d219-1e38-4e15-a058-051a46d4cf55",
      "content": {
        "_uid": "0934afaa-6ce3-4926-b8fa-a6fd069525fc",
        "link": "https://cdslab.uni-ak.ac.at",
        "component": "page_department",
        "part_of_institute": {
          "name": "Institut für Kunst & Gesellschaft",
          "id": "1700b229-93dd-40d1-af1e-3553e880743b",
          "url": "",
          "linktype": "story",
          "fieldtype": "multilink",
          "cached_url": "2022/data/data-institutes/institut-fuer-kunst-gesellschaft"
        }
      },
      "slug": "cross-disciplinary-strategies",
      "full_slug": "abteilungen/cross-disciplinary-strategies",
      "sort_by_date": null,
      "position": -280,
      "tag_list": [],
      "is_startpage": false,
      "parent_id": 95693957,
      "meta_data": null,
      "group_id": "9e8e146b-67d1-482b-8a75-55343b93169f",
      "first_published_at": "2022-01-21T07:33:54.437Z",
      "release_id": null,
      "lang": "default",
      "path": null,
      "alternates": [],
      "default_full_slug": null,
      "translated_slugs": null
    },
    {
      "name": "Expanded Museum Studies",
      "created_at": "2022-01-21T07:30:33.563Z",
      "published_at": "2022-01-21T10:48:32.000Z",
      "id": 100297893,
      "uuid": "c478225d-10bd-40e7-818b-d8937b2b6f9a",
      "content": {
        "_uid": "8b2537ac-3123-46e8-8545-b6bdd0822187",
        "link": "https://www.dieangewandte.at/expandedmuseumstudies",
        "component": "page_department",
        "part_of_institute": {
          "name": "Institut für Kunstwissenschaften, Kunstpädagogik und Kunstvermittlung",
          "id": "d8b5c660-5a62-4c8b-99c6-8d7f8770f9ce",
          "url": "",
          "linktype": "story",
          "fieldtype": "multilink",
          "cached_url": "2022/data/data-institutes/institut-fuer-kunstwissenschaften-kunstpaedagogik-und-kunstvermittlung"
        }
      },
      "slug": "expanded-museum-studies",
      "full_slug": "abteilungen/expanded-museum-studies",
      "sort_by_date": null,
      "position": -270,
      "tag_list": [],
      "is_startpage": false,
      "parent_id": 95693957,
      "meta_data": null,
      "group_id": "1337f261-8b3c-4048-ab5f-9c7c39f8629d",
      "first_published_at": "2022-01-21T07:33:54.437Z",
      "release_id": null,
      "lang": "default",
      "path": null,
      "alternates": [],
      "default_full_slug": null,
      "translated_slugs": null
    },
    {
      "name": "Kunst- und Kulturwissenschaften",
      "created_at": "2022-01-21T07:30:23.185Z",
      "published_at": "2022-01-21T10:48:32.000Z",
      "id": 100297892,
      "uuid": "ddb3e761-c60d-4680-9c70-d629b6829110",
      "content": {
        "_uid": "81b7c059-f4a6-4a0e-a61f-5f1707e8943d",
        "link": "https://www.dieangewandte.at/KuWi",
        "component": "page_department",
        "part_of_institute": {
          "name": "Institut für Kunstwissenschaften, Kunstpädagogik und Kunstvermittlung",
          "id": "d8b5c660-5a62-4c8b-99c6-8d7f8770f9ce",
          "url": "",
          "linktype": "story",
          "fieldtype": "multilink",
          "cached_url": "2022/data/data-institutes/institut-fuer-kunstwissenschaften-kunstpaedagogik-und-kunstvermittlung"
        }
      },
      "slug": "kunst-und-kulturwissenschaften",
      "full_slug": "abteilungen/kunst-und-kulturwissenschaften",
      "sort_by_date": null,
      "position": -260,
      "tag_list": [],
      "is_startpage": false,
      "parent_id": 95693957,
      "meta_data": null,
      "group_id": "e324560a-773b-49e5-84e3-f094ae92b04b",
      "first_published_at": "2022-01-21T07:33:54.437Z",
      "release_id": null,
      "lang": "default",
      "path": null,
      "alternates": [],
      "default_full_slug": null,
      "translated_slugs": null
    },
    {
      "name": "Textil - Freie, angewandte und experimentelle künstlerische Gestaltung",
      "created_at": "2022-01-21T07:30:13.429Z",
      "published_at": "2022-01-21T10:48:32.000Z",
      "id": 100297891,
      "uuid": "53a48a5f-c948-4d06-9ce0-d58f259450b4",
      "content": {
        "_uid": "c48bebca-cac3-42c0-8773-e4233577833d",
        "link": "https://uni-ak.at",
        "component": "page_department",
        "part_of_institute": {
          "name": "Institut für Kunstwissenschaften, Kunstpädagogik und Kunstvermittlung",
          "id": "d8b5c660-5a62-4c8b-99c6-8d7f8770f9ce",
          "url": "",
          "linktype": "story",
          "fieldtype": "multilink",
          "cached_url": "2022/data/data-institutes/institut-fuer-kunstwissenschaften-kunstpaedagogik-und-kunstvermittlung"
        }
      },
      "slug": "textil-freie-angewandte-und-experimentelle-kuenstlerische-gestaltung",
      "full_slug": "abteilungen/textil-freie-angewandte-und-experimentelle-kuenstlerische-gestaltung",
      "sort_by_date": null,
      "position": -250,
      "tag_list": [],
      "is_startpage": false,
      "parent_id": 95693957,
      "meta_data": null,
      "group_id": "ca1d650c-d6d1-46a4-bc4d-323afa0dbe5a",
      "first_published_at": "2022-01-21T07:33:54.437Z",
      "release_id": null,
      "lang": "default",
      "path": null,
      "alternates": [],
      "default_full_slug": null,
      "translated_slugs": null
    },
    {
      "name": "Kunst und Kommunikative Praxis",
      "created_at": "2022-01-21T07:30:02.263Z",
      "published_at": "2022-01-21T10:48:32.000Z",
      "id": 100297888,
      "uuid": "b6e41a3c-7d78-4b4b-ada9-cc4f0d7505be",
      "content": {
        "_uid": "79a41bf0-440d-42e2-bdd2-7d3a2c3d39cf",
        "link": "https://uni-ak.at",
        "component": "page_department",
        "part_of_institute": {
          "name": "Institut für Kunstwissenschaften, Kunstpädagogik und Kunstvermittlung",
          "id": "d8b5c660-5a62-4c8b-99c6-8d7f8770f9ce",
          "url": "",
          "linktype": "story",
          "fieldtype": "multilink",
          "cached_url": "2022/data/data-institutes/institut-fuer-kunstwissenschaften-kunstpaedagogik-und-kunstvermittlung"
        }
      },
      "slug": "kunst-und-kommunikative-praxis",
      "full_slug": "abteilungen/kunst-und-kommunikative-praxis",
      "sort_by_date": null,
      "position": -240,
      "tag_list": [],
      "is_startpage": false,
      "parent_id": 95693957,
      "meta_data": null,
      "group_id": "f97942ae-b3e7-4086-ac7f-74ef9e547761",
      "first_published_at": "2022-01-21T07:33:54.437Z",
      "release_id": null,
      "lang": "default",
      "path": null,
      "alternates": [],
      "default_full_slug": null,
      "translated_slugs": null
    },
    {
      "name": "Design, Architektur und Environment für Kunstpädagogik",
      "created_at": "2022-01-21T07:29:49.060Z",
      "published_at": "2022-01-21T10:48:32.000Z",
      "id": 100297887,
      "uuid": "af396cb3-9186-4be0-80a8-a5be587d69ad",
      "content": {
        "_uid": "e43f0a60-a31a-4ec0-beed-902b02e3d5d5",
        "link": "https://uni-ak.at",
        "component": "page_department",
        "part_of_institute": {
          "name": "Institut für Kunstwissenschaften, Kunstpädagogik und Kunstvermittlung",
          "id": "d8b5c660-5a62-4c8b-99c6-8d7f8770f9ce",
          "url": "",
          "linktype": "story",
          "fieldtype": "multilink",
          "cached_url": "2022/data/data-institutes/institut-fuer-kunstwissenschaften-kunstpaedagogik-und-kunstvermittlung"
        }
      },
      "slug": "design-architektur-und-environment-fuer-kunstpaedagogik",
      "full_slug": "abteilungen/design-architektur-und-environment-fuer-kunstpaedagogik",
      "sort_by_date": null,
      "position": -230,
      "tag_list": [],
      "is_startpage": false,
      "parent_id": 95693957,
      "meta_data": null,
      "group_id": "75c753f9-7797-454b-8839-b02900896490",
      "first_published_at": "2022-01-21T07:33:54.437Z",
      "release_id": null,
      "lang": "default",
      "path": null,
      "alternates": [],
      "default_full_slug": null,
      "translated_slugs": null
    },
    {
      "name": "Cultural Heritage Conservation and Management",
      "created_at": "2022-01-21T07:29:27.148Z",
      "published_at": "2022-01-21T10:48:32.000Z",
      "id": 100297886,
      "uuid": "78a59c3e-a4d1-428b-88f2-da349c2cc253",
      "content": {
        "_uid": "649555ad-fe25-45d4-afbb-1fbf26fd21eb",
        "link": "https://konservierung-restaurierung.uni-ak.ac.at",
        "component": "page_department",
        "part_of_institute": {
          "name": "Institut für Konservierung & Restaurierung",
          "id": "654ca025-b675-4837-a381-6dbe757dbcb1",
          "url": "",
          "linktype": "story",
          "fieldtype": "multilink",
          "cached_url": "2022/data/data-institutes/institut-fuer-konservierung-restaurierung"
        }
      },
      "slug": "cultural-heritage-conservation-and-management",
      "full_slug": "abteilungen/cultural-heritage-conservation-and-management",
      "sort_by_date": null,
      "position": -220,
      "tag_list": [],
      "is_startpage": false,
      "parent_id": 95693957,
      "meta_data": null,
      "group_id": "ca247f69-c31c-43f4-9165-613e8eb1808a",
      "first_published_at": "2022-01-21T07:33:54.437Z",
      "release_id": null,
      "lang": "default",
      "path": null,
      "alternates": [],
      "default_full_slug": null,
      "translated_slugs": null
    },
    {
      "name": "Konservierung & Restaurierung",
      "created_at": "2022-01-21T07:29:00.747Z",
      "published_at": "2022-01-21T10:48:32.000Z",
      "id": 100297608,
      "uuid": "83a32ebf-eda0-4ab6-bbd3-9a5db01528d4",
      "content": {
        "_uid": "36bd0ed4-39b0-4c88-ba0d-2f2f09d09eeb",
        "link": "https://konservierung-restaurierung.uni-ak.ac.at",
        "component": "page_department",
        "part_of_institute": {
          "name": "Institut für Konservierung & Restaurierung",
          "id": "654ca025-b675-4837-a381-6dbe757dbcb1",
          "url": "",
          "linktype": "story",
          "fieldtype": "multilink",
          "cached_url": "2022/data/data-institutes/institut-fuer-konservierung-restaurierung"
        }
      },
      "slug": "konservierung-restaurierung",
      "full_slug": "abteilungen/konservierung-restaurierung",
      "sort_by_date": null,
      "position": -210,
      "tag_list": [],
      "is_startpage": false,
      "parent_id": 95693957,
      "meta_data": null,
      "group_id": "e87e917e-11b1-4086-a002-9215b7cb1d16",
      "first_published_at": "2022-01-21T07:33:54.437Z",
      "release_id": null,
      "lang": "default",
      "path": null,
      "alternates": [],
      "default_full_slug": null,
      "translated_slugs": null
    },
    {
      "name": "Experimental Game Cultures",
      "created_at": "2022-01-21T07:28:49.522Z",
      "published_at": "2022-01-21T10:48:32.000Z",
      "id": 100297553,
      "uuid": "a26afb0a-198a-4482-83c4-780a0fa3c70f",
      "content": {
        "_uid": "3e6b7f20-910f-4417-b864-3d93bdbf92a3",
        "link": "https://www.dieangewandte.at/experimentalgamecultures",
        "component": "page_department",
        "part_of_institute": {
          "name": "Institut für Design",
          "id": "47b1d5df-725e-46c2-a4e4-cca2b61100a5",
          "url": "",
          "linktype": "story",
          "fieldtype": "multilink",
          "cached_url": "2022/data/data-institutes/institut-fuer-design"
        }
      },
      "slug": "experimental-game-cultures",
      "full_slug": "abteilungen/experimental-game-cultures",
      "sort_by_date": null,
      "position": -200,
      "tag_list": [],
      "is_startpage": false,
      "parent_id": 95693957,
      "meta_data": null,
      "group_id": "908379a4-c3aa-474a-b89d-b426cb845f05",
      "first_published_at": "2022-01-21T07:33:54.437Z",
      "release_id": null,
      "lang": "default",
      "path": null,
      "alternates": [],
      "default_full_slug": null,
      "translated_slugs": null
    },
    {
      "name": "Mode",
      "created_at": "2022-01-21T07:28:34.916Z",
      "published_at": "2022-01-21T10:48:32.000Z",
      "id": 100297552,
      "uuid": "587245af-a2a7-42a2-87dc-1d703b81a742",
      "content": {
        "_uid": "873feca9-d92d-4d51-ba56-f55a1e9df491",
        "link": "https://www.modeklasse.net",
        "component": "page_department",
        "part_of_institute": {
          "name": "Institut für Design",
          "id": "47b1d5df-725e-46c2-a4e4-cca2b61100a5",
          "url": "",
          "linktype": "story",
          "fieldtype": "multilink",
          "cached_url": "2022/data/data-institutes/institut-fuer-design"
        }
      },
      "slug": "mode",
      "full_slug": "abteilungen/mode",
      "sort_by_date": null,
      "position": -190,
      "tag_list": [],
      "is_startpage": false,
      "parent_id": 95693957,
      "meta_data": null,
      "group_id": "13f8508b-6090-4240-93e4-11dd3a9919f9",
      "first_published_at": "2022-01-21T07:33:54.437Z",
      "release_id": null,
      "lang": "default",
      "path": null,
      "alternates": [],
      "default_full_slug": null,
      "translated_slugs": null
    },
    {
      "name": "Industrial Design 2",
      "created_at": "2022-01-21T07:28:24.096Z",
      "published_at": "2022-01-21T10:48:32.000Z",
      "id": 100297551,
      "uuid": "96a21e6b-6970-411b-9ca4-15bf47f33240",
      "content": {
        "_uid": "147c4fcb-06c8-471b-8dd8-b4bf92f2c30f",
        "link": "https://designinvestigations.at",
        "component": "page_department",
        "part_of_institute": {
          "name": "Institut für Design",
          "id": "47b1d5df-725e-46c2-a4e4-cca2b61100a5",
          "url": "",
          "linktype": "story",
          "fieldtype": "multilink",
          "cached_url": "2022/data/data-institutes/institut-fuer-design"
        }
      },
      "slug": "industrial-design-2",
      "full_slug": "abteilungen/industrial-design-2",
      "sort_by_date": null,
      "position": -180,
      "tag_list": [],
      "is_startpage": false,
      "parent_id": 95693957,
      "meta_data": null,
      "group_id": "ae13f7d8-56ad-4727-baf6-10bd98f21773",
      "first_published_at": "2022-01-21T07:33:54.437Z",
      "release_id": null,
      "lang": "default",
      "path": null,
      "alternates": [],
      "default_full_slug": null,
      "translated_slugs": null
    },
    {
      "name": "Industrial Design 1",
      "created_at": "2022-01-21T07:28:12.151Z",
      "published_at": "2022-01-21T10:48:32.000Z",
      "id": 100297550,
      "uuid": "9669285a-004c-4972-8be8-abb74b183ef7",
      "content": {
        "_uid": "45929981-e0b8-40a0-83d7-238296f95958",
        "link": "https://www.instituteofdesign.at",
        "component": "page_department",
        "part_of_institute": {
          "name": "Institut für Design",
          "id": "47b1d5df-725e-46c2-a4e4-cca2b61100a5",
          "url": "",
          "linktype": "story",
          "fieldtype": "multilink",
          "cached_url": "2022/data/data-institutes/institut-fuer-design"
        }
      },
      "slug": "industrial-design-1",
      "full_slug": "abteilungen/industrial-design-1",
      "sort_by_date": null,
      "position": -170,
      "tag_list": [],
      "is_startpage": false,
      "parent_id": 95693957,
      "meta_data": null,
      "group_id": "e530c12b-3aef-4c59-bea7-994487c15758",
      "first_published_at": "2022-01-21T07:33:54.437Z",
      "release_id": null,
      "lang": "default",
      "path": null,
      "alternates": [],
      "default_full_slug": null,
      "translated_slugs": null
    },
    {
      "name": "Grafik und Werbung",
      "created_at": "2022-01-21T07:28:00.780Z",
      "published_at": "2022-01-21T10:48:32.000Z",
      "id": 100297548,
      "uuid": "29a5e3f2-6345-4719-9638-aa0a3e837559",
      "content": {
        "_uid": "75d5acac-b63e-475f-8baa-f8097da32f4f",
        "link": "http://www.klassefuerideen.at/Startseite.3.0.html",
        "component": "page_department",
        "part_of_institute": {
          "name": "Institut für Design",
          "id": "47b1d5df-725e-46c2-a4e4-cca2b61100a5",
          "url": "",
          "linktype": "story",
          "fieldtype": "multilink",
          "cached_url": "2022/data/data-institutes/institut-fuer-design"
        }
      },
      "slug": "grafik-und-werbung",
      "full_slug": "abteilungen/grafik-und-werbung",
      "sort_by_date": null,
      "position": -160,
      "tag_list": [],
      "is_startpage": false,
      "parent_id": 95693957,
      "meta_data": null,
      "group_id": "01f0a2e8-e79d-4b82-ab09-c3d239325249",
      "first_published_at": "2022-01-21T07:33:54.437Z",
      "release_id": null,
      "lang": "default",
      "path": null,
      "alternates": [],
      "default_full_slug": null,
      "translated_slugs": null
    },
    {
      "name": "Angewandte Fotografie & zeitbasierte Medien",
      "created_at": "2022-01-21T07:27:37.973Z",
      "published_at": "2022-01-21T10:48:32.000Z",
      "id": 100297493,
      "uuid": "72ca519e-8fc4-4a79-8768-1c9a0a3a438f",
      "content": {
        "_uid": "30d8ea62-92ab-4834-8e00-2f8ac031aedd",
        "link": "https://www.applied-photography.at",
        "component": "page_department",
        "part_of_institute": {
          "name": "Institut für Design",
          "id": "47b1d5df-725e-46c2-a4e4-cca2b61100a5",
          "url": "",
          "linktype": "story",
          "fieldtype": "multilink",
          "cached_url": "2022/data/data-institutes/institut-fuer-design"
        }
      },
      "slug": "angewandte-fotografie-zeitbasierte-medien",
      "full_slug": "abteilungen/angewandte-fotografie-zeitbasierte-medien",
      "sort_by_date": null,
      "position": -150,
      "tag_list": [],
      "is_startpage": false,
      "parent_id": 95693957,
      "meta_data": null,
      "group_id": "b775db1c-dfe8-4f65-886f-ef97bda96f93",
      "first_published_at": "2022-01-21T07:33:54.437Z",
      "release_id": null,
      "lang": "default",
      "path": null,
      "alternates": [],
      "default_full_slug": null,
      "translated_slugs": null
    },
    {
      "name": "Transmediale Kunst",
      "created_at": "2022-01-21T07:27:23.460Z",
      "published_at": "2022-01-21T10:48:32.000Z",
      "id": 100297491,
      "uuid": "92cc6fb1-86d0-4bc1-b552-ac18e92e49b3",
      "content": {
        "_uid": "1be4808e-af52-4a52-82ba-e005e3a34505",
        "link": "https://transmedialekunst.com",
        "component": "page_department",
        "part_of_institute": {
          "name": "Institut für Bildende und Mediale Kunst",
          "id": "6254ee49-af66-43ca-9c11-6006509d4fda",
          "url": "",
          "linktype": "story",
          "fieldtype": "multilink",
          "cached_url": "2022/data/data-institutes/institut-fuer-bildende-und-mediale-kunst"
        }
      },
      "slug": "transmediale-kunst",
      "full_slug": "abteilungen/transmediale-kunst",
      "sort_by_date": null,
      "position": -140,
      "tag_list": [],
      "is_startpage": false,
      "parent_id": 95693957,
      "meta_data": null,
      "group_id": "3abf40af-cfb3-4233-89a0-85d6e8165d19",
      "first_published_at": "2022-01-21T07:33:54.437Z",
      "release_id": null,
      "lang": "default",
      "path": null,
      "alternates": [],
      "default_full_slug": null,
      "translated_slugs": null
    },
    {
      "name": "TransArts",
      "created_at": "2022-01-21T07:27:09.479Z",
      "published_at": "2022-01-21T10:48:32.000Z",
      "id": 100297489,
      "uuid": "cc581ba5-354f-4c58-9b56-fa76daeff54f",
      "content": {
        "_uid": "e8842109-821d-4374-a98e-b0fc60f16cb8",
        "link": "https://www.transarts.at",
        "component": "page_department",
        "part_of_institute": {
          "name": "Institut für Bildende und Mediale Kunst",
          "id": "6254ee49-af66-43ca-9c11-6006509d4fda",
          "url": "",
          "linktype": "story",
          "fieldtype": "multilink",
          "cached_url": "2022/data/data-institutes/institut-fuer-bildende-und-mediale-kunst"
        }
      },
      "slug": "transarts",
      "full_slug": "abteilungen/transarts",
      "sort_by_date": null,
      "position": -130,
      "tag_list": [],
      "is_startpage": false,
      "parent_id": 95693957,
      "meta_data": null,
      "group_id": "dbf60a94-f4a8-44f7-bdcb-39e70cebe14d",
      "first_published_at": "2022-01-21T07:33:54.437Z",
      "release_id": null,
      "lang": "default",
      "path": null,
      "alternates": [],
      "default_full_slug": null,
      "translated_slugs": null
    },
    {
      "name": "Ortsbezogene Kunst",
      "created_at": "2022-01-21T07:26:44.672Z",
      "published_at": "2022-01-21T10:48:32.000Z",
      "id": 100297488,
      "uuid": "4843ee9a-13f5-48d2-8352-9294322d6b9f",
      "content": {
        "_uid": "c5bd8b9a-9090-477d-aa85-7cd570c5b2f5",
        "link": "http://www.ortsbezogenekunst.at",
        "component": "page_department",
        "part_of_institute": {
          "name": "Institut für Bildende und Mediale Kunst",
          "id": "6254ee49-af66-43ca-9c11-6006509d4fda",
          "url": "",
          "linktype": "story",
          "fieldtype": "multilink",
          "cached_url": "2022/data/data-institutes/institut-fuer-bildende-und-mediale-kunst"
        }
      },
      "slug": "ortsbezogene-kunst",
      "full_slug": "abteilungen/ortsbezogene-kunst",
      "sort_by_date": null,
      "position": -120,
      "tag_list": [],
      "is_startpage": false,
      "parent_id": 95693957,
      "meta_data": null,
      "group_id": "53ebd4f8-17ab-44e2-b8b1-fc6c8d935fa3",
      "first_published_at": "2022-01-21T07:33:54.437Z",
      "release_id": null,
      "lang": "default",
      "path": null,
      "alternates": [],
      "default_full_slug": null,
      "translated_slugs": null
    },
    {
      "name": "Malerei & Animationsfilm",
      "created_at": "2022-01-21T07:26:33.687Z",
      "published_at": "2022-01-21T10:48:32.000Z",
      "id": 100297487,
      "uuid": "b9ce027c-46aa-4647-aa99-310fd1a64274",
      "content": {
        "_uid": "2c40debd-1337-4353-bcaa-ad8371821936",
        "link": "https://klassejuditheisler.uni-ak.ac.at",
        "component": "page_department",
        "part_of_institute": {
          "name": "Institut für Bildende und Mediale Kunst",
          "id": "6254ee49-af66-43ca-9c11-6006509d4fda",
          "url": "",
          "linktype": "story",
          "fieldtype": "multilink",
          "cached_url": "2022/data/data-institutes/institut-fuer-bildende-und-mediale-kunst"
        }
      },
      "slug": "malerei-animationsfilm",
      "full_slug": "abteilungen/malerei-animationsfilm",
      "sort_by_date": null,
      "position": -110,
      "tag_list": [],
      "is_startpage": false,
      "parent_id": 95693957,
      "meta_data": null,
      "group_id": "dbef10d0-dacc-47e0-97d1-d9711d7e9fa6",
      "first_published_at": "2022-01-21T07:33:54.437Z",
      "release_id": null,
      "lang": "default",
      "path": null,
      "alternates": [],
      "default_full_slug": null,
      "translated_slugs": null
    },
    {
      "name": "Malerei",
      "created_at": "2022-01-21T07:26:22.700Z",
      "published_at": "2022-01-21T10:48:32.000Z",
      "id": 100297486,
      "uuid": "445431a1-638b-46bc-84fa-b4cea3becf9e",
      "content": {
        "_uid": "e5724163-4ade-4d76-9e6a-9142066cea8d",
        "link": "https://abteilungmalerei.uni-ak.ac.at",
        "component": "page_department",
        "part_of_institute": {
          "name": "Institut für Bildende und Mediale Kunst",
          "id": "6254ee49-af66-43ca-9c11-6006509d4fda",
          "url": "",
          "linktype": "story",
          "fieldtype": "multilink",
          "cached_url": "2022/data/data-institutes/institut-fuer-bildende-und-mediale-kunst"
        }
      },
      "slug": "malerei",
      "full_slug": "abteilungen/malerei",
      "sort_by_date": null,
      "position": -100,
      "tag_list": [],
      "is_startpage": false,
      "parent_id": 95693957,
      "meta_data": null,
      "group_id": "cfa378f1-d27d-4c17-b861-e35dd0918c3c",
      "first_published_at": "2022-01-21T07:33:54.437Z",
      "release_id": null,
      "lang": "default",
      "path": null,
      "alternates": [],
      "default_full_slug": null,
      "translated_slugs": null
    },
    {
      "name": "Grafik- und Druckgrafik",
      "created_at": "2022-01-21T07:26:12.441Z",
      "published_at": "2022-01-21T10:48:32.000Z",
      "id": 100297485,
      "uuid": "dff38438-5148-4deb-933e-6352e9a1367e",
      "content": {
        "_uid": "ffcc0ce2-48f4-447c-9e5a-ba3f72124a96",
        "link": "https://grafik.ac.at",
        "component": "page_department",
        "part_of_institute": {
          "name": "Institut für Bildende und Mediale Kunst",
          "id": "6254ee49-af66-43ca-9c11-6006509d4fda",
          "url": "",
          "linktype": "story",
          "fieldtype": "multilink",
          "cached_url": "2022/data/data-institutes/institut-fuer-bildende-und-mediale-kunst"
        }
      },
      "slug": "grafik-und-druckgrafik",
      "full_slug": "abteilungen/grafik-und-druckgrafik",
      "sort_by_date": null,
      "position": -90,
      "tag_list": [],
      "is_startpage": false,
      "parent_id": 95693957,
      "meta_data": null,
      "group_id": "9a85ff4b-8394-4fad-91b3-e0bcacd03ca3",
      "first_published_at": "2022-01-21T07:33:54.437Z",
      "release_id": null,
      "lang": "default",
      "path": null,
      "alternates": [],
      "default_full_slug": null,
      "translated_slugs": null
    },
    {
      "name": "Fotografie",
      "created_at": "2022-01-21T07:26:01.972Z",
      "published_at": "2022-01-21T10:48:32.000Z",
      "id": 100297483,
      "uuid": "5c5b01aa-8cb5-4573-b8b0-060ba8cc21b1",
      "content": {
        "_uid": "2dfcbf27-b1c7-4c2c-ab52-f724639124cc",
        "link": "https://klassefotografie.at",
        "component": "page_department",
        "part_of_institute": {
          "name": "Institut für Bildende und Mediale Kunst",
          "id": "6254ee49-af66-43ca-9c11-6006509d4fda",
          "url": "",
          "linktype": "story",
          "fieldtype": "multilink",
          "cached_url": "2022/data/data-institutes/institut-fuer-bildende-und-mediale-kunst"
        }
      },
      "slug": "fotografie",
      "full_slug": "abteilungen/fotografie",
      "sort_by_date": null,
      "position": -80,
      "tag_list": [],
      "is_startpage": false,
      "parent_id": 95693957,
      "meta_data": null,
      "group_id": "bc099702-1918-4497-bc0c-a639f6aa6f10",
      "first_published_at": "2022-01-21T07:33:54.437Z",
      "release_id": null,
      "lang": "default",
      "path": null,
      "alternates": [],
      "default_full_slug": null,
      "translated_slugs": null
    },
    {
      "name": "Digitale Kunst",
      "created_at": "2022-01-21T07:25:48.025Z",
      "published_at": "2022-01-21T10:48:32.000Z",
      "id": 100297449,
      "uuid": "6a8f1546-9729-4c5b-bb96-1ca104162894",
      "content": {
        "_uid": "7f15bcfc-b7c1-4cf5-9b04-4c6f1c2e096a",
        "link": "https://digitalekunst.ac.at",
        "component": "page_department",
        "part_of_institute": {
          "name": "Institut für Bildende und Mediale Kunst",
          "id": "6254ee49-af66-43ca-9c11-6006509d4fda",
          "url": "",
          "linktype": "story",
          "fieldtype": "multilink",
          "cached_url": "2022/data/data-institutes/institut-fuer-bildende-und-mediale-kunst"
        }
      },
      "slug": "digitale-kunst",
      "full_slug": "abteilungen/digitale-kunst",
      "sort_by_date": null,
      "position": -70,
      "tag_list": [],
      "is_startpage": false,
      "parent_id": 95693957,
      "meta_data": null,
      "group_id": "06f736ff-d70a-4c0a-8191-306488de5ffe",
      "first_published_at": "2022-01-21T07:33:54.437Z",
      "release_id": null,
      "lang": "default",
      "path": null,
      "alternates": [],
      "default_full_slug": null,
      "translated_slugs": null
    },
    {
      "name": "Bühnen- & Filmgestaltung",
      "created_at": "2022-01-21T07:25:34.414Z",
      "published_at": "2022-01-21T10:48:32.000Z",
      "id": 100297427,
      "uuid": "aa800f3d-eaff-42b4-bc1c-d1a058a3f658",
      "content": {
        "_uid": "18832770-e00c-4ad2-993e-4d599b4bed72",
        "link": "http://buehne.dieangewandte.at/jart/prj3/angewandte_buehne/main.jart?rel=de&content-id=1473160493708&reserve-mode=active",
        "component": "page_department",
        "part_of_institute": {
          "name": "Institut für Bildende und Mediale Kunst",
          "id": "6254ee49-af66-43ca-9c11-6006509d4fda",
          "url": "",
          "linktype": "story",
          "fieldtype": "multilink",
          "cached_url": "2022/data/data-institutes/institut-fuer-bildende-und-mediale-kunst"
        }
      },
      "slug": "buehnen-filmgestaltung",
      "full_slug": "abteilungen/buehnen-filmgestaltung",
      "sort_by_date": null,
      "position": -60,
      "tag_list": [],
      "is_startpage": false,
      "parent_id": 95693957,
      "meta_data": null,
      "group_id": "bdd13630-447d-4e19-93a5-41c226265daa",
      "first_published_at": "2022-01-21T07:33:54.437Z",
      "release_id": null,
      "lang": "default",
      "path": null,
      "alternates": [],
      "default_full_slug": null,
      "translated_slugs": null
    },
    {
      "name": "Art & Science",
      "created_at": "2022-01-21T07:25:22.604Z",
      "published_at": "2022-01-21T10:48:32.000Z",
      "id": 100297426,
      "uuid": "45faa55b-2436-4a1e-bd3b-4cdf6b3d309f",
      "content": {
        "_uid": "5bb629fa-a895-4b4a-8fbc-c1596b78a73f",
        "link": "http://artscience.uni-ak.ac.at",
        "component": "page_department",
        "part_of_institute": {
          "name": "Institut für Bildende und Mediale Kunst",
          "id": "6254ee49-af66-43ca-9c11-6006509d4fda",
          "url": "",
          "linktype": "story",
          "fieldtype": "multilink",
          "cached_url": "2022/data/data-institutes/institut-fuer-bildende-und-mediale-kunst"
        }
      },
      "slug": "art-science",
      "full_slug": "abteilungen/art-science",
      "sort_by_date": null,
      "position": -50,
      "tag_list": [],
      "is_startpage": false,
      "parent_id": 95693957,
      "meta_data": null,
      "group_id": "7548d12c-e9e7-48fe-be32-cfa64035d99d",
      "first_published_at": "2022-01-21T07:33:54.437Z",
      "release_id": null,
      "lang": "default",
      "path": null,
      "alternates": [],
      "default_full_slug": null,
      "translated_slugs": null
    },
    {
      "name": "Architekturentwurf 3",
      "created_at": "2022-01-21T07:24:44.460Z",
      "published_at": "2022-01-21T10:48:32.000Z",
      "id": 100297424,
      "uuid": "d916e46b-3eb8-4bf9-8b22-296509d2ccfe",
      "content": {
        "_uid": "26c96bad-f512-44bb-982d-4c38ec774b17",
        "link": "https://ioa.angewandte.at",
        "component": "page_department",
        "part_of_institute": {
          "name": "Institut für Architektur",
          "id": "fa78ba6c-3751-4927-88dc-3462d25dffde",
          "url": "",
          "linktype": "story",
          "fieldtype": "multilink",
          "cached_url": "2022/data/data-institutes/institut-fuer-architektur"
        }
      },
      "slug": "architekturentwurf-3",
      "full_slug": "abteilungen/architekturentwurf-3",
      "sort_by_date": null,
      "position": -40,
      "tag_list": [],
      "is_startpage": false,
      "parent_id": 95693957,
      "meta_data": null,
      "group_id": "23b39bde-e09d-44c9-b28b-da03149d292a",
      "first_published_at": "2022-01-21T07:33:54.437Z",
      "release_id": null,
      "lang": "default",
      "path": null,
      "alternates": [],
      "default_full_slug": null,
      "translated_slugs": null
    },
    {
      "name": "Architekturentwurf 2",
      "created_at": "2022-01-21T07:24:29.512Z",
      "published_at": "2022-01-21T10:48:32.000Z",
      "id": 100297423,
      "uuid": "f2b43c26-f0ac-498f-8b25-717230bc95c1",
      "content": {
        "_uid": "b67319c6-4c4e-4b26-8111-a70097716fbd",
        "link": "https://ioa.angewandte.at",
        "component": "page_department",
        "part_of_institute": {
          "name": "Institut für Architektur",
          "id": "fa78ba6c-3751-4927-88dc-3462d25dffde",
          "url": "",
          "linktype": "story",
          "fieldtype": "multilink",
          "cached_url": "2022/data/data-institutes/institut-fuer-architektur"
        }
      },
      "slug": "architekturentwurf-2",
      "full_slug": "abteilungen/architekturentwurf-2",
      "sort_by_date": null,
      "position": -30,
      "tag_list": [],
      "is_startpage": false,
      "parent_id": 95693957,
      "meta_data": null,
      "group_id": "49d2d125-9c12-4125-b133-3a55ef2cccdf",
      "first_published_at": "2022-01-21T07:33:54.437Z",
      "release_id": null,
      "lang": "default",
      "path": null,
      "alternates": [],
      "default_full_slug": null,
      "translated_slugs": null
    },
    {
      "name": "Architekturentwurf 1",
      "created_at": "2022-01-21T07:19:05.563Z",
      "published_at": "2022-01-21T10:48:32.000Z",
      "id": 100297318,
      "uuid": "a896ec9a-32cb-49d9-b334-a7b7404924b9",
      "content": {
        "_uid": "ded4d2be-ca2f-4f6d-b729-2905927d81e5",
        "link": "https://ioa.angewandte.at",
        "name": "",
        "component": "page_department",
        "part_of_institute": {
          "name": "Institut für Architektur",
          "id": "fa78ba6c-3751-4927-88dc-3462d25dffde",
          "url": "",
          "linktype": "story",
          "fieldtype": "multilink",
          "cached_url": "2022/data/data-institutes/institut-fuer-architektur"
        }
      },
      "slug": "architekturentwurf-1",
      "full_slug": "abteilungen/architekturentwurf-1",
      "sort_by_date": null,
      "position": -20,
      "tag_list": [],
      "is_startpage": false,
      "parent_id": 95693957,
      "meta_data": null,
      "group_id": "dfe92fd1-d94a-4690-ac22-ef7b6fb1f454",
      "first_published_at": "2022-01-21T07:33:54.437Z",
      "release_id": null,
      "lang": "default",
      "path": null,
      "alternates": [],
      "default_full_slug": null,
      "translated_slugs": null
    },
    {
      "name": "Skulptur und Raum",
      "created_at": "2022-01-05T20:21:12.468Z",
      "published_at": "2022-01-21T10:48:32.000Z",
      "id": 96377719,
      "uuid": "74e4cc6d-45a4-46f0-a1df-d635f20b7c11",
      "content": {
        "_uid": "453dd57c-2c8e-43c8-9738-6ff1db645ab3",
        "link": "https://www.skulpturundraum.at",
        "component": "page_department",
        "part_of_institute": {
          "name": "Institut für Bildende und Mediale Kunst",
          "id": "6254ee49-af66-43ca-9c11-6006509d4fda",
          "url": "",
          "linktype": "story",
          "fieldtype": "multilink",
          "cached_url": "2022/data/data-institutes/institut-fuer-bildende-und-mediale-kunst"
        }
      },
      "slug": "skulptur-und-raum",
      "full_slug": "abteilungen/skulptur-und-raum",
      "sort_by_date": null,
      "position": -10,
      "tag_list": [],
      "is_startpage": false,
      "parent_id": 95693957,
      "meta_data": null,
      "group_id": "9ade258a-8387-4461-8f91-fd84bb21f8c9",
      "first_published_at": "2022-01-17T20:04:32.650Z",
      "release_id": null,
      "lang": "default",
      "path": null,
      "alternates": [],
      "default_full_slug": null,
      "translated_slugs": null
    },
    {
      "name": "Grafik Design",
      "created_at": "2022-01-03T21:12:32.813Z",
      "published_at": "2022-01-21T10:48:32.000Z",
      "id": 95693958,
      "uuid": "fcc727e4-ac31-4d10-9339-b6f4d8c3a807",
      "content": {
        "_uid": "5037e31f-2b2e-48ae-8721-aa1895a490f4",
        "link": "https://www.klassekartak.com",
        "component": "page_department",
        "part_of_institute": {
          "name": "Institut für Design",
          "id": "47b1d5df-725e-46c2-a4e4-cca2b61100a5",
          "url": "",
          "linktype": "story",
          "fieldtype": "multilink",
          "cached_url": "2022/data/data-institutes/institut-fuer-design"
        }
      },
      "slug": "grafik-design",
      "full_slug": "abteilungen/grafik-design",
      "sort_by_date": null,
      "position": 0,
      "tag_list": [],
      "is_startpage": false,
      "parent_id": 95693957,
      "meta_data": null,
      "group_id": "875822b6-99e2-4a1a-8a45-98d353b5ebe0",
      "first_published_at": "2022-01-17T20:04:32.650Z",
      "release_id": null,
      "lang": "default",
      "path": null,
      "alternates": [],
      "default_full_slug": null,
      "translated_slugs": null
    }
  ],
  "cv": 1648205776,
  "rels": [],
  "links": []
}